[
  {
    "header": "Pronájem bytu 2+1 57 m²",
    "Address": "Schwaigrova, Brno - Komárov",
    "Price": "17 500 Kč/měsíc",
    "link": "https://www.sreality.cz/detail/pronajem/byt/2+1/brno-komarov-schwaigrova/3940823884",
    "id": "3940823884"
  },
  {
    "header": "Pronájem bytu 3+kk 93 m²",
    "Address": "Hlinky, Brno - Staré Brno",
    "Price": "29 500 Kč/měsíc",
    "link": "https://www.sreality.cz/detail/pronajem/byt/3+kk/brno-stare-brno-hlinky/4127601484",
    "id": "4127601484"
  },
  {
    "header": "Pronájem bytu 3+kk 65 m²",
    "Address": "Dřevařská, Brno - Veveří",
    "Price": "19 990 Kč/měsíc",
    "link": "https://www.sreality.cz/detail/pronajem/byt/3+kk/brno-veveri-drevarska/4109882188",
    "id": "4109882188"
  },
  {
    "header": "Pronájem bytu 2+1 79 m²",
    "Address": "Zahradnická, Brno - Staré Brno",
    "Price": "23 000 Kč/měsíc",
    "link": "https://www.sreality.cz/detail/pronajem/byt/2+1/brno-stare-brno-zahradnicka/913032012",
    "id": "913032012"
  },
  {
    "header": "Pronájem bytu 3+kk 89 m²",
    "Address": "Nové sady, Brno - Staré Brno",
    "Price": "39 800 Kč/měsíc",
    "link": "https://www.sreality.cz/detail/pronajem/byt/3+kk/brno-stare-brno-nove-sady/4238984012",
    "id": "4238984012"
  },
  {
    "header": "Pronájem bytu 3+kk 96 m²",
    "Address": "Příkop, Brno - Zábrdovice",
    "Price": "26 500 Kč/měsíc",
    "link": "https://www.sreality.cz/detail/pronajem/byt/3+kk/brno-zabrdovice-prikop/2749731660",
    "id": "2749731660"
  },
  {
    "header": "Pronájem bytu 3+1 97 m²",
    "Address": "Čápkova, Brno - Veveří",
    "Price": "30 000 Kč/měsíc",
    "link": "https://www.sreality.cz/detail/pronajem/byt/3+1/brno-veveri-capkova/3041522508",
    "id": "3041522508"
  },
  {
    "header": "Pronájem bytu 2+1 68 m²",
    "Address": "Kolískova, Brno - Trnitá",
    "Price": "19 900 Kč/měsíc",
    "link": "https://www.sreality.cz/detail/pronajem/byt/2+1/brno-trnita-koliskova/3546428236",
    "id": "3546428236"
  },
  {
    "header": "Pronájem bytu 3+kk 73 m²",
    "Address": "Chudčická, Brno - Bystrc",
    "Price": "21 000 Kč/měsíc",
    "link": "https://www.sreality.cz/detail/pronajem/byt/3+kk/brno-bystrc-chudcicka/1460192076",
    "id": "1460192076"
  },
  {
    "header": "Pronájem bytu 2+1 54 m²",
    "Address": "Vysoká, Brno - Štýřice",
    "Price": "21 500 Kč/měsíc",
    "link": "https://www.sreality.cz/detail/pronajem/byt/2+1/brno-styrice-vysoka/476980044",
    "id": "476980044"
  },
  {
    "header": "Pronájem bytu 2+1 54 m²",
    "Address": "Hlinky, Brno - Staré Brno",
    "Price": "21 900 Kč/měsíc",
    "link": "https://www.sreality.cz/detail/pronajem/byt/2+1/brno-stare-brno-hlinky/486785868",
    "id": "486785868"
  },
  {
    "header": "Pronájem bytu 3+1 63 m²",
    "Address": "Havelkova, Brno - Bohunice",
    "Price": "22 000 Kč/měsíc",
    "link": "https://www.sreality.cz/detail/pronajem/byt/3+1/brno-bohunice-havelkova/600949580",
    "id": "600949580"
  },
  {
    "header": "Pronájem bytu 3+kk 65 m²",
    "Address": "Alešova, Brno - Černá Pole",
    "Price": "25 500 Kč/měsíc",
    "link": "https://www.sreality.cz/detail/pronajem/byt/3+kk/brno-cerna-pole-alesova/486859596",
    "id": "486859596"
  },
  {
    "header": "Pronájem bytu 3+kk 127 m²",
    "Address": "Skorkovského, Brno - Židenice",
    "Price": "22 000 Kč/měsíc",
    "link": "https://www.sreality.cz/detail/pronajem/byt/3+kk/brno-zidenice-skorkovskeho/1784554316",
    "id": "1784554316"
  },
  {
    "header": "Pronájem bytu 2+1 52 m²",
    "Address": "Jožky Jabůrkové, Brno - Komín",
    "Price": "18 000 Kč/měsíc",
    "link": "https://www.sreality.cz/detail/pronajem/byt/2+1/brno-komin-jozky-jaburkove/3447845708",
    "id": "3447845708"
  },
  {
    "header": "Pronájem bytu 3+1 72 m²",
    "Address": "Jaselská, Brno - Veveří",
    "Price": "25 000 Kč/měsíc",
    "link": "https://www.sreality.cz/detail/pronajem/byt/3+1/brno-veveri-jaselska/1104147276",
    "id": "1104147276"
  },
  {
    "header": "Pronájem bytu 3+kk 95 m²",
    "Address": "Opuštěná, Brno - Trnitá",
    "Price": "29 990 Kč/měsíc",
    "link": "https://www.sreality.cz/detail/pronajem/byt/3+kk/brno-trnita-opustena/3691524940",
    "id": "3691524940"
  },
  {
    "header": "Pronájem bytu 2+1 60 m²",
    "Address": "Borodinova, Brno - Kohoutovice",
    "Price": "19 900 Kč/měsíc",
    "link": "https://www.sreality.cz/detail/pronajem/byt/2+1/brno-kohoutovice-borodinova/3703911244",
    "id": "3703911244"
  },
  {
    "header": "Pronájem bytu 2+1 67 m²",
    "Address": "Brno - Zábrdovice",
    "Price": "17 000 Kč/měsíc",
    "link": "https://www.sreality.cz/detail/pronajem/byt/2+1/brno-zabrdovice-/274539340",
    "id": "274539340"
  },
  {
    "header": "Pronájem bytu 2+1 61 m²",
    "Address": "Jungmannova, Brno - Královo Pole",
    "Price": "15 000 Kč/měsíc",
    "link": "https://www.sreality.cz/detail/pronajem/byt/2+1/brno-kralovo-pole-jungmannova/474817356",
    "id": "474817356"
  },
  {
    "header": "Pronájem bytu 3+1 73 m²",
    "Address": "Vondrákova, Brno - Bystrc",
    "Price": "19 000 Kč/měsíc",
    "link": "https://www.sreality.cz/detail/pronajem/byt/3+1/brno-bystrc-vondrakova/21832524",
    "id": "21832524"
  }
]