[
  {
    "header": "Pronájem bytu 3+kk 80 m²",
    "Address": "Fuchsova, Brno - Trnitá",
    "Price": "35 000 Kč/měsíc",
    "link": "https://www.sreality.cz/detail/pronajem/byt/3+kk/brno-trnita-fuchsova/1537901388",
    "id": "1537901388"
  },
  {
    "header": "Pronájem bytu 2+1 62 m²",
    "Address": "Zemědělská, Brno - Černá Pole",
    "Price": "26 900 Kč/měsíc",
    "link": "https://www.sreality.cz/detail/pronajem/byt/2+1/brno-cerna-pole-zemedelska/1349964620",
    "id": "1349964620"
  },
  {
    "header": "Pronájem bytu 2+1 54 m²",
    "Address": "Spáčilova, Brno - Černovice",
    "Price": "16 000 Kč/měsíc",
    "link": "https://www.sreality.cz/detail/pronajem/byt/2+1/brno-cernovice-spacilova/3680949068",
    "id": "3680949068"
  },
  {
    "header": "Pronájem bytu 3+kk 98 m²",
    "Address": "Kopečná, Brno - Staré Brno",
    "Price": "37 500 Kč/měsíc",
    "link": "https://www.sreality.cz/detail/pronajem/byt/3+kk/brno-stare-brno-kopecna/1631114060",
    "id": "1631114060"
  },
  {
    "header": "Pronájem bytu 3+kk 81 m²",
    "Address": "třída Generála Píky, Brno - Černá Pole",
    "Price": "34 800 Kč/měsíc",
    "link": "https://www.sreality.cz/detail/pronajem/byt/3+kk/brno-cerna-pole-trida-generala-piky/1451086668",
    "id": "1451086668"
  },
  {
    "header": "Pronájem bytu 3+1 97 m²",
    "Address": "Čápkova, Brno - Veveří",
    "Price": "30 000 Kč/měsíc",
    "link": "https://www.sreality.cz/detail/pronajem/byt/3+1/brno-veveri-capkova/3041522508",
    "id": "3041522508"
  },
  {
    "header": "Pronájem bytu 3+kk 96 m²",
    "Address": "Příkop, Brno - Zábrdovice",
    "Price": "26 500 Kč/měsíc",
    "link": "https://www.sreality.cz/detail/pronajem/byt/3+kk/brno-zabrdovice-prikop/2749731660",
    "id": "2749731660"
  },
  {
    "header": "Pronájem bytu 3+kk 75 m²",
    "Address": "Jana Uhra, Brno - Veveří",
    "Price": "24 000 Kč/měsíc",
    "link": "https://www.sreality.cz/detail/pronajem/byt/3+kk/brno-veveri-jana-uhra/839635788",
    "id": "839635788"
  },
  {
    "header": "Pronájem bytu 3+kk 79 m²",
    "Address": "Novodvorská, Brno - Žebětín",
    "Price": "23 000 Kč/měsíc",
    "link": "https://www.sreality.cz/detail/pronajem/byt/3+kk/brno-zebetin-novodvorska/1473434444",
    "id": "1473434444"
  },
  {
    "header": "Pronájem bytu 3+1 80 m²",
    "Address": "Teyschlova, Brno - Bystrc",
    "Price": "20 900 Kč/měsíc",
    "link": "https://www.sreality.cz/detail/pronajem/byt/3+1/brno-bystrc-teyschlova/4289188684",
    "id": "4289188684"
  },
  {
    "header": "Pronájem bytu 2+1 70 m²",
    "Address": "Došlíkova, Brno - Židenice",
    "Price": "21 000 Kč/měsíc",
    "link": "https://www.sreality.cz/detail/pronajem/byt/2+1/brno-zidenice-doslikova/1794102092",
    "id": "1794102092"
  },
  {
    "header": "Pronájem bytu 3+kk 74 m²",
    "Address": "Fryčajova, Brno - Obřany",
    "Price": "23 800 Kč/měsíc",
    "link": "https://www.sreality.cz/detail/pronajem/byt/3+kk/brno-obrany-frycajova/1153291084",
    "id": "1153291084"
  },
  {
    "header": "Pronájem bytu 2+1 69 m²",
    "Address": "Kobližná, Brno - Brno-město",
    "Price": "30 000 Kč/měsíc",
    "link": "https://www.sreality.cz/detail/pronajem/byt/2+1/brno-brno-mesto-koblizna/2508649292",
    "id": "2508649292"
  },
  {
    "header": "Pronájem bytu 3+1 111 m²",
    "Address": "Berkova, Brno - Královo Pole",
    "Price": "5 000 Kč/měsíc",
    "link": "https://www.sreality.cz/detail/pronajem/byt/3+1/brno-kralovo-pole-berkova/3385316172",
    "id": "3385316172"
  },
  {
    "header": "Pronájem bytu 3+kk 78 m²",
    "Address": "Ptašínského, Brno - Ponava",
    "Price": "25 000 Kč/měsíc",
    "link": "https://www.sreality.cz/detail/pronajem/byt/3+kk/brno-ponava-ptasinskeho/1255179084",
    "id": "1255179084"
  },
  {
    "header": "Pronájem bytu 2+1 73 m²",
    "Address": "Jana Uhra, Brno - Veveří",
    "Price": "25 000 Kč/měsíc",
    "link": "https://www.sreality.cz/detail/pronajem/byt/2+1/brno-veveri-jana-uhra/2562446156",
    "id": "2562446156"
  },
  {
    "header": "Pronájem bytu 2+1 57 m²",
    "Address": "Merhautova, Brno - Černá Pole",
    "Price": "15 600 Kč/měsíc",
    "link": "https://www.sreality.cz/detail/pronajem/byt/2+1/brno-cerna-pole-merhautova/1300751180",
    "id": "1300751180"
  },
  {
    "header": "Pronájem bytu 3+kk 65 m²",
    "Address": "Dřevařská, Brno - Veveří",
    "Price": "19 990 Kč/měsíc",
    "link": "https://www.sreality.cz/detail/pronajem/byt/3+kk/brno-veveri-drevarska/4109882188",
    "id": "4109882188"
  },
  {
    "header": "Pronájem bytu 2+1 52 m²",
    "Address": "Křídlovická, Brno - Staré Brno",
    "Price": "16 500 Kč/měsíc",
    "link": "https://www.sreality.cz/detail/pronajem/byt/2+1/brno-stare-brno-kridlovicka/3941004108",
    "id": "3941004108"
  },
  {
    "header": "Pronájem bytu 3+kk 70 m²",
    "Address": "Banskobystrická, Brno - Řečkovice",
    "Price": "21 500 Kč/měsíc",
    "link": "https://www.sreality.cz/detail/pronajem/byt/3+kk/brno-reckovice-banskobystricka/1127080780",
    "id": "1127080780"
  }
]