[
  {
    "header": "Pronájem bytu 3+1 103 m²",
    "Address": "Jakubské náměstí, Brno - Brno-město",
    "Price": "33 000 Kč/měsíc",
    "link": "https://www.sreality.cz/detail/pronajem/byt/3+1/brno-brno-mesto-jakubske-namesti/3797192780",
    "id": "3797192780"
  },
  {
    "header": "Pronájem bytu 2+1 65 m²",
    "Address": "Jindřichova, Brno - Žabovřesky",
    "Price": "19 000 Kč/měsíc",
    "link": "https://www.sreality.cz/detail/pronajem/byt/2+1/brno-zabovresky-jindrichova/385720396",
    "id": "385720396"
  },
  {
    "header": "Pronájem bytu 3+1 80 m²",
    "Address": "Škrétova, Brno - Řečkovice",
    "Price": "24 000 Kč/měsíc",
    "link": "https://www.sreality.cz/detail/pronajem/byt/3+1/brno-reckovice-skretova/3861614668",
    "id": "3861614668"
  },
  {
    "header": "Pronájem bytu 2+1 55 m²",
    "Address": "Ibsenova, Brno - Lesná",
    "Price": "19 000 Kč/měsíc",
    "link": "https://www.sreality.cz/detail/pronajem/byt/2+1/brno-lesna-ibsenova/1462472780",
    "id": "1462472780"
  },
  {
    "header": "Pronájem bytu 3+1 72 m²",
    "Address": "Milady Horákové, Brno - Zábrdovice",
    "Price": "24 000 Kč/měsíc",
    "link": "https://www.sreality.cz/detail/pronajem/byt/3+1/brno-zabrdovice-milady-horakove/3637157964",
    "id": "3637157964"
  },
  {
    "header": "Pronájem bytu 3+1 70 m²",
    "Address": "Jurkovičova, Brno - Lesná",
    "Price": "22 000 Kč/měsíc",
    "link": "https://www.sreality.cz/detail/pronajem/byt/3+1/brno-lesna-jurkovicova/2043322444",
    "id": "2043322444"
  },
  {
    "header": "Pronájem bytu 3+1 62 m²",
    "Address": "Dunajská, Brno - Starý Lískovec",
    "Price": "22 000 Kč/měsíc",
    "link": "https://www.sreality.cz/detail/pronajem/byt/3+1/brno-stary-liskovec-dunajska/1622909004",
    "id": "1622909004"
  },
  {
    "header": "Pronájem bytu 3+kk 91 m²",
    "Address": "třída Generála Píky, Brno",
    "Price": "47 000 Kč/měsíc",
    "link": "https://www.sreality.cz/detail/pronajem/byt/3+kk/brno-brno-trida-generala-piky/3868700748",
    "id": "3868700748"
  },
  {
    "header": "Pronájem bytu 2+1 52 m²",
    "Address": "Křížová, Brno - Staré Brno",
    "Price": "20 400 Kč/měsíc",
    "link": "https://www.sreality.cz/detail/pronajem/byt/2+1/brno-stare-brno-krizova/296595532",
    "id": "296595532"
  },
  {
    "header": "Pronájem bytu 3+kk 87 m²",
    "Address": "Hlinky, Brno - Staré Brno",
    "Price": "31 500 Kč/měsíc",
    "link": "https://www.sreality.cz/detail/pronajem/byt/3+kk/brno-stare-brno-hlinky/3887894604",
    "id": "3887894604"
  },
  {
    "header": "Pronájem bytu 3+kk 73 m²",
    "Address": "Kopečná, Brno - Staré Brno",
    "Price": "21 000 Kč/měsíc",
    "link": "https://www.sreality.cz/detail/pronajem/byt/3+kk/brno-stare-brno-kopecna/2441183308",
    "id": "2441183308"
  },
  {
    "header": "Pronájem bytu 2+1 60 m²",
    "Address": "Chládkova, Brno - Žabovřesky",
    "Price": "7 500 Kč/měsíc",
    "link": "https://www.sreality.cz/detail/pronajem/byt/2+1/brno-zabovresky-chladkova/1925091404",
    "id": "1925091404"
  },
  {
    "header": "Pronájem bytu 2+1 62 m²",
    "Address": "Chládkova, Brno - Žabovřesky",
    "Price": "20 800 Kč/měsíc",
    "link": "https://www.sreality.cz/detail/pronajem/byt/2+1/brno-zabovresky-chladkova/1869250636",
    "id": "1869250636"
  },
  {
    "header": "Pronájem bytu 3+kk 100 m²",
    "Address": "Majdalenky, Brno - Lesná",
    "Price": "35 000 Kč/měsíc",
    "link": "https://www.sreality.cz/detail/pronajem/byt/3+kk/brno-lesna-majdalenky/2444402764",
    "id": "2444402764"
  },
  {
    "header": "Pronájem bytu 2+1 55 m²",
    "Address": "Vlhká, Brno - Zábrdovice",
    "Price": "23 295 Kč/měsíc",
    "link": "https://www.sreality.cz/detail/pronajem/byt/2+1/brno-zabrdovice-vlhka/4054941772",
    "id": "4054941772"
  },
  {
    "header": "Pronájem bytu 3+kk 73 m²",
    "Address": "Říčanská, Brno - Bystrc",
    "Price": "23 990 Kč/měsíc",
    "link": "https://www.sreality.cz/detail/pronajem/byt/3+kk/brno-bystrc-ricanska/4094575436",
    "id": "4094575436"
  },
  {
    "header": "Pronájem bytu 2+1 46 m²",
    "Address": "Hvězdová, Brno - Zábrdovice",
    "Price": "18 000 Kč/měsíc",
    "link": "https://www.sreality.cz/detail/pronajem/byt/2+1/brno-zabrdovice-hvezdova/194555980",
    "id": "194555980"
  },
  {
    "header": "Pronájem bytu 3+1 71 m²",
    "Address": "Mikulčická, Brno - Slatina",
    "Price": "20 800 Kč/měsíc",
    "link": "https://www.sreality.cz/detail/pronajem/byt/3+1/brno-slatina-mikulcicka/1357807692",
    "id": "1357807692"
  },
  {
    "header": "Pronájem bytu 3+1 64 m²",
    "Address": "Vrbenského, Brno - Komín",
    "Price": "20 500 Kč/měsíc",
    "link": "https://www.sreality.cz/detail/pronajem/byt/3+1/brno-komin-vrbenskeho/716673100",
    "id": "716673100"
  },
  {
    "header": "Pronájem bytu 3+1 68 m²",
    "Address": "Horní, Brno - Štýřice",
    "Price": "25 000 Kč/měsíc",
    "link": "https://www.sreality.cz/detail/pronajem/byt/3+1/brno-styrice-horni/1116975180",
    "id": "1116975180"
  },
  {
    "header": "Pronájem bytu 2+1 50 m²",
    "Address": "Havlišova, Brno - Královo Pole",
    "Price": "21 500 Kč/měsíc",
    "link": "https://www.sreality.cz/detail/pronajem/byt/2+1/brno-kralovo-pole-havlisova/4037115980",
    "id": "4037115980"
  }
]