[
  {
    "header": "Pronájem bytu 3+kk 75 m²",
    "Address": "Komárovská, Brno - Komárov",
    "Price": "49 000 Kč/měsíc",
    "link": "https://www.sreality.cz/detail/pronajem/byt/3+kk/brno-komarov-komarovska/3643315020",
    "id": "3643315020"
  },
  {
    "header": "Pronájem bytu 3+1 78 m²",
    "Address": "Slunečná, Brno - Nový Lískovec",
    "Price": "20 000 Kč/měsíc",
    "link": "https://www.sreality.cz/detail/pronajem/byt/3+1/brno-novy-liskovec-slunecna/1638892364",
    "id": "1638892364"
  },
  {
    "header": "Pronájem bytu 3+kk 72 m²",
    "Address": "Merhautova, Brno - Zábrdovice",
    "Price": "24 000 Kč/měsíc",
    "link": "https://www.sreality.cz/detail/pronajem/byt/3+kk/brno-zabrdovice-merhautova/2982253388",
    "id": "2982253388"
  },
  {
    "header": "Pronájem bytu 3+kk 82 m²",
    "Address": "Kopečná, Brno - Staré Brno",
    "Price": "30 900 Kč/měsíc",
    "link": "https://www.sreality.cz/detail/pronajem/byt/3+kk/brno-stare-brno-kopecna/768193356",
    "id": "768193356"
  },
  {
    "header": "Pronájem bytu 3+kk 79 m²",
    "Address": "Hvozdecká, Brno - Bystrc",
    "Price": "22 900 Kč/měsíc",
    "link": "https://www.sreality.cz/detail/pronajem/byt/3+kk/brno-bystrc-hvozdecka/4074697548",
    "id": "4074697548"
  },
  {
    "header": "Pronájem bytu 3+1 65 m²",
    "Address": "Šaumannova, Brno - Židenice",
    "Price": "21 000 Kč/měsíc",
    "link": "https://www.sreality.cz/detail/pronajem/byt/3+1/brno-zidenice-saumannova/3930911564",
    "id": "3930911564"
  },
  {
    "header": "Pronájem bytu 3+kk 73 m²",
    "Address": "Říčanská, Brno - Bystrc",
    "Price": "25 990 Kč/měsíc",
    "link": "https://www.sreality.cz/detail/pronajem/byt/3+kk/brno-bystrc-ricanska/610923340",
    "id": "610923340"
  },
  {
    "header": "Pronájem bytu 3+kk 80 m²",
    "Address": "Jakubské náměstí, Brno - Brno-město",
    "Price": "28 500 Kč/měsíc",
    "link": "https://www.sreality.cz/detail/pronajem/byt/3+kk/brno-brno-mesto-jakubske-namesti/1285653324",
    "id": "1285653324"
  },
  {
    "header": "Pronájem bytu 3+kk 117 m²",
    "Address": "Brno - Černá Pole",
    "Price": "32 000 Kč/měsíc",
    "link": "https://www.sreality.cz/detail/pronajem/byt/3+kk/brno-cerna-pole-/1413776204",
    "id": "1413776204"
  },
  {
    "header": "Pronájem bytu 3+kk 110 m²",
    "Address": "náměstí Svobody, Brno - Brno-město",
    "Price": "40 000 Kč/měsíc",
    "link": "https://www.sreality.cz/detail/pronajem/byt/3+kk/brno-brno-mesto-namesti-svobody/1265431372",
    "id": "1265431372"
  },
  {
    "header": "Pronájem bytu 3+kk 70 m²",
    "Address": "Řípská, Brno - Slatina",
    "Price": "25 900 Kč/měsíc",
    "link": "https://www.sreality.cz/detail/pronajem/byt/3+kk/brno-slatina-ripska/983495500",
    "id": "983495500"
  },
  {
    "header": "Pronájem bytu 3+kk 82 m²",
    "Address": "Spolková, Brno - Zábrdovice",
    "Price": "35 000 Kč/měsíc",
    "link": "https://www.sreality.cz/detail/pronajem/byt/3+kk/brno-zabrdovice-spolkova/3559297868",
    "id": "3559297868"
  },
  {
    "header": "Pronájem bytu 3+kk 73 m²",
    "Address": "Spolková, Brno - Zábrdovice",
    "Price": "28 000 Kč/měsíc",
    "link": "https://www.sreality.cz/detail/pronajem/byt/3+kk/brno-zabrdovice-spolkova/3814326860",
    "id": "3814326860"
  },
  {
    "header": "Pronájem bytu 2+1 50 m²",
    "Address": "Fillova, Brno - Lesná",
    "Price": "19 000 Kč/měsíc",
    "link": "https://www.sreality.cz/detail/pronajem/byt/2+1/brno-lesna-fillova/544011084",
    "id": "544011084"
  },
  {
    "header": "Pronájem bytu 3+kk 122 m²",
    "Address": "Merhautova, Brno - Černá Pole",
    "Price": "29 990 Kč/měsíc",
    "link": "https://www.sreality.cz/detail/pronajem/byt/3+kk/brno-cerna-pole-merhautova/2571825996",
    "id": "2571825996"
  },
  {
    "header": "Pronájem bytu 3+1 72 m²",
    "Address": "Vsetínská, Brno - Štýřice",
    "Price": "23 000 Kč/měsíc",
    "link": "https://www.sreality.cz/detail/pronajem/byt/3+1/brno-styrice-vsetinska/1688073036",
    "id": "1688073036"
  },
  {
    "header": "Pronájem bytu 3+kk 96 m²",
    "Address": "Příkop, Brno - Zábrdovice",
    "Price": "28 000 Kč/měsíc",
    "link": "https://www.sreality.cz/detail/pronajem/byt/3+kk/brno-zabrdovice-prikop/2749731660",
    "id": "2749731660"
  },
  {
    "header": "Pronájem bytu 3+1 71 m²",
    "Address": "Žebětínská, Brno - Kohoutovice",
    "Price": "23 000 Kč/měsíc",
    "link": "https://www.sreality.cz/detail/pronajem/byt/3+1/brno-kohoutovice-zebetinska/3127804748",
    "id": "3127804748"
  },
  {
    "header": "Pronájem bytu 3+kk 68 m²",
    "Address": "Stojanova, Brno - Veveří",
    "Price": "27 000 Kč/měsíc",
    "link": "https://www.sreality.cz/detail/pronajem/byt/3+kk/brno-veveri-stojanova/2923098956",
    "id": "2923098956"
  },
  {
    "header": "Pronájem bytu 3+1 82 m²",
    "Address": "Kotlářská, Brno - Veveří",
    "Price": "25 000 Kč/měsíc",
    "link": "https://www.sreality.cz/detail/pronajem/byt/3+1/brno-veveri-kotlarska/2664297292",
    "id": "2664297292"
  }
]